pyjiracloudapi/__init__.py
pyjiracloudapi/pyjiracloudapi.py
pyjiracloudapi-1.0.0.dist-info/LICENSE.txt
pyjiracloudapi-1.0.0.dist-info/METADATA
pyjiracloudapi-1.0.0.dist-info/WHEEL
pyjiracloudapi-1.0.0.dist-info/top_level.txt
pyjiracloudapi-1.0.0.dist-info/RECORD
