Metadata-Version: 2.1
Name: pyjiracloudapi
Version: 1.0.0
Summary: python3 module to call jiracloud apis in command line or inside a module.
Home-page: https://github.com/stormalf/pyjiracloudapi
Author: Stormalf
Author-email: stormalf.dev@gmail.com
License: UNKNOWN
Project-URL: Bug Reports, https://github.com/stormalf/pyjiracloudapi/issues
Project-URL: Source, https://github.com/stormalf/pyjiracloudapi/
Keywords: pyjiracloudapi
Platform: UNKNOWN
Classifier: Development Status :: 3 - Alpha
Classifier: Intended Audience :: Developers
Classifier: Topic :: Software Development :: Build Tools
Classifier: License :: OSI Approved :: MIT License
Classifier: Programming Language :: Python :: 3
Classifier: Programming Language :: Python :: 3.6
Classifier: Programming Language :: Python :: 3.7
Classifier: Programming Language :: Python :: 3.8
Classifier: Programming Language :: Python :: 3.9
Classifier: Programming Language :: Python :: 3 :: Only
Requires-Python: >=3.6, <4
License-File: LICENSE.txt
Requires-Dist: cryptography
Requires-Dist: setuptools (>=40.8.0)
Requires-Dist: wheel
Requires-Dist: argparse
Requires-Dist: requests
